{
  "id": "delth_transit_hub",
  "name": "戴司中轉站",
  "regionId": "crambell",
  "districtId": "crambell_delth",
  "locationType": "sublocation",
  "parentId": "delth_patrol_zone",
  "tags": ["outdoor", "transit", "checkpoint"],
  "base": {
    "description": "管制轉移場，連接戴司與其他象限的中轉站。守衛在此嚴格追蹤通行證與人員流動。",
    "ambience": ["檢查哨", "軌道", "迴盪的腳步聲", "行政壓力"],
    "connections": [
      {
        "targetLocationId": "delth_patrol_zone",
        "description": "返回巡邏管制區"
      },
      {
        "targetLocationId": "famein_transit_hub",
        "description": "前往費敏的轉移路線",
        "travelNote": "搭乘前往費敏中轉站的管制班次。",
        "access": {
          "itemRequirements": [
            { "itemId": "transit_pass", "variantId": "famein" }
          ],
          "lockedMessage": "需持有費敏通行證。"
        }
      },
      {
        "targetLocationId": "pestilens_transit_hub",
        "description": "前往帕絲蒂蘭斯的轉移路線",
        "travelNote": "搭乘前往帕絲蒂蘭斯中轉站的管制班次。",
        "access": {
          "itemRequirements": [
            { "itemId": "transit_pass", "variantId": "pestilens" }
          ],
          "lockedMessage": "需持有帕絲蒂蘭斯通行證。"
        }
      },
      {
        "targetLocationId": "wyar_transit_hub",
        "description": "前往瓦爾的轉移路線",
        "travelNote": "搭乘前往瓦爾中轉站的管制班次。",
        "access": {
          "timeRanges": [
            {
              "startHour": 0,
              "startMinute": 0,
              "endHour": 5,
              "endMinute": 59
            }
          ],
          "itemRequirements": [
            { "itemId": "transit_pass", "variantId": "wyar" }
          ],
          "lockedMessage": "需持有瓦爾通行證。"
        }
      },
      {
        "targetLocationId": "konquer_outer_gate",
        "description": "前往康庫爾的通道路線",
        "travelNote": "另有一條通道通往康庫爾。",
        "access": {
          "itemRequirements": [
            { "itemId": "konquer_access_pass" }
          ],
          "lockedMessage": "需持有康庫爾通行證。"
        }
      }
    ],
    "npcIds": [],
    "eventIds": [],
    "isAccessible": true
  },
  "localVariants": []
}
